[
  {
    "id": "service_001",
    "type": "service",
    "title": "Поставка спецтехники",
    "content": "Компания занимается поставкой спецтехники для бизнеса"
  },
  {
    "id": "service_002",
    "type": "service",
    "title": "Сервис и ремонт",
    "content": "Компания оказывает сервисное обслуживание и ремонт техники"
  },
  {
    "id": "advantage_001",
    "type": "advantage",
    "title": "Большой ассортимент запчастей",
    "content": "В наличии более 10 000 наименований запчастей"
  },
  {
    "id": "advantage_002",
    "type": "advantage",
    "title": "Официальный дилер",
    "content": "Компания является официальным дилером техники"
  },
  {
    "id": "segment_001",
    "type": "segment",
    "title": "Горнодобывающие компании",
    "content": "Компания работает с горнодобывающими предприятиями"
  },
  {
    "id": "brand_001",
    "type": "brand",
    "title": "SINOTRUK",
    "content": "Компания предлагает технику бренда SINOTRUK"
  }
]
